Metadata-Version: 2.4
Name: llama-index-readers-opensearch
Version: 0.4.1
Summary: llama-index readers opensearch integration
Author-email: Your Name <you@example.com>
Maintainer: chnsagitchen
License-Expression: MIT
License-File: LICENSE
Requires-Python: <4.0,>=3.9
Requires-Dist: llama-index-core<0.15,>=0.13.0
Requires-Dist: opensearch-py<3,>=2.4.2
